plutoplots/__init__.py
plutoplots/plot.py
plutoplots-0.4.8.dist-info/LICENSE
plutoplots-0.4.8.dist-info/WHEEL
plutoplots-0.4.8.dist-info/METADATA
plutoplots-0.4.8.dist-info/RECORD
