Metadata-Version: 2.1
Name: plutoplots
Version: 0.4.8
Summary: visualization 
Author-email: Oluwole Ilesanmi <oluwoleilesanmi@gmail.com>
Classifier: License :: OSI Approved :: MIT License
Project-URL: Home, https://github.com/oluwoleilesanmi/pluto
